pyttee/__init__.py
pyttee/builder.py
pyttee/compiler.py
pyttee/core.py
pyttee/models.py
pyttee/parser.py
pyttee-0.1.2.dist-info/LICENSE.txt
pyttee-0.1.2.dist-info/METADATA
pyttee-0.1.2.dist-info/WHEEL
pyttee-0.1.2.dist-info/RECORD
